github_repo_opener/__init__.py
github_repo_opener/__version__.py
github_repo_opener-0.1.2.dist-info/LICENSE
github_repo_opener-0.1.2.dist-info/METADATA
github_repo_opener-0.1.2.dist-info/WHEEL
github_repo_opener-0.1.2.dist-info/entry_points.txt
github_repo_opener-0.1.2.dist-info/top_level.txt
github_repo_opener-0.1.2.dist-info/RECORD
