Metadata-Version: 1.2
Name: github_repo_opener
Version: 0.1.2
Summary: A tool to open your GitHub repository page quickly.
Home-page: https://github.com/gh640/github_repo_opener
Author: Goto Hayato
Author-email: habita.gh@gmail.com
License: MIT
Keywords: github repository
Platform: UNKNOWN
Classifier: Environment :: Console
Classifier: Intended Audience :: Developers
Classifier: License :: OSI Approved :: MIT License
Classifier: Operating System :: MacOS
Classifier: Operating System :: Microsoft :: Windows
Classifier: Operating System :: POSIX :: Linux
Classifier: Programming Language :: Python
Classifier: Programming Language :: Python :: 3.4
Classifier: Programming Language :: Python :: 3.5
Classifier: Programming Language :: Python :: 3.6
Classifier: Programming Language :: Python :: 3.7
Classifier: Topic :: Software Development
Classifier: Topic :: Software Development :: Version Control :: Git
Classifier: Topic :: Utilities
Requires-Python: >=3.4
